{
 "SoundBanksInfo": {
  "Platform": "Windows",
  "BasePlatform": "Windows",
  "SchemaVersion": "16",
  "SoundBankVersion": "154",
  "SoundBanks": [
   {
    "Id": "3161908922",
    "Type": "User",
    "GUID": "{AEA877A2-151C-40A2-9839-4843226CD743}",
    "Language": "SFX",
    "Hash": "{B8B92A19-2993-6409-3EEC-BD561B42807C}",
    "ObjectPath": "\\SoundBanks\\Default Work Unit\\main",
    "ShortName": "main",
    "Path": "main.bnk",
    "Media": [
     {
      "Id": "5830356",
      "Language": "SFX",
      "Streaming": "false",
      "Location": "Memory",
      "ShortName": "SFX_TreeOfLife_02.wav",
      "CachePath": "E6/{E6D8EEF2-5909-A1A1-C237-E994551BDB79}.wem"
     },
     {
      "Id": "21657060",
      "Language": "SFX",
      "Streaming": "false",
      "Location": "Memory",
      "ShortName": "Dance of the Spirit.wav",
      "CachePath": "90/{90C2E0D6-1FE6-4791-3429-757E8E72D21F}.wem"
     },
     {
      "Id": "79160856",
      "Language": "SFX",
      "Streaming": "false",
      "Location": "Memory",
      "ShortName": "SFX_Banshee_Attack.wav",
      "CachePath": "B0/{B0006C82-9CB6-D8A5-B74C-B7C9B3B73B98}.wem"
     },
     {
      "Id": "93382910",
      "Language": "SFX",
      "Streaming": "false",
      "Location": "Memory",
      "ShortName": "SFX_Steps_Grass_01.wav",
      "CachePath": "27/{27A5BF69-C286-085C-3B83-0581F20CC77A}.wem"
     },
     {
      "Id": "102221775",
      "Language": "SFX",
      "Streaming": "false",
      "Location": "Memory",
      "ShortName": "SFX_Pooka_Fall.wav",
      "CachePath": "9F/{9F708306-95E7-2D20-F181-7813FE3B31A5}.wem"
     },
     {
      "Id": "111375023",
      "Language": "SFX",
      "Streaming": "false",
      "Location": "Memory",
      "ShortName": "SFX_Button_02.wav",
      "CachePath": "02/{02FDA0F8-6D92-6A94-B4ED-93D6DC19A683}.wem"
     },
     {
      "Id": "113287012",
      "Language": "SFX",
      "Streaming": "false",
      "Location": "Memory",
      "ShortName": "SFX_Steps_Wood_01.wav",
      "CachePath": "26/{26166825-8DA0-CA26-F9E4-5A7BC312980D}.wem"
     },
     {
      "Id": "121922950",
      "Language": "SFX",
      "Streaming": "false",
      "Location": "Memory",
      "ShortName": "SFX_MC_Dash.wav",
      "CachePath": "49/{492C46B5-FBBF-5AFB-6F6A-AD8235AF2B98}.wem"
     },
     {
      "Id": "153266711",
      "Language": "SFX",
      "Streaming": "false",
      "Location": "Memory",
      "ShortName": "SFX_Steps_Rock_01.wav",
      "CachePath": "8F/{8F6D9380-2041-8B97-26B0-6CFAE9D01B4D}.wem"
     },
     {
      "Id": "226908720",
      "Language": "SFX",
      "Streaming": "false",
      "Location": "Memory",
      "ShortName": "SFX_Cave_03.wav",
      "CachePath": "E0/{E0E69BEA-D88A-92B3-6B26-5A6D9F3F19B4}.wem"
     },
     {
      "Id": "237654140",
      "Language": "SFX",
      "Streaming": "false",
      "Location": "Memory",
      "ShortName": "SFX_TreeOfLife_03.wav",
      "CachePath": "46/{46261E3F-D11A-FDA6-6E1B-3D7EF788416F}.wem"
     },
     {
      "Id": "275805708",
      "Language": "SFX",
      "Streaming": "false",
      "Location": "Memory",
      "ShortName": "SFX_MC_NormalAttack_01.wav",
      "CachePath": "46/{4644840C-4733-ACBC-90CF-60258B44A349}.wem"
     },
     {
      "Id": "285188273",
      "Language": "SFX",
      "Streaming": "false",
      "Location": "Memory",
      "ShortName": "SFX_Pooka_Jump.wav",
      "CachePath": "C2/{C28D5A20-F7CC-7A4E-C196-8F44B6ED2B38}.wem"
     },
     {
      "Id": "303434784",
      "Language": "SFX",
      "Streaming": "false",
      "Location": "Memory",
      "ShortName": "SFX_Cave_02.wav",
      "CachePath": "C4/{C4C3A2AF-1107-6B0E-D001-AB7509B27014}.wem"
     },
     {
      "Id": "327978205",
      "Language": "SFX",
      "Streaming": "false",
      "Location": "Memory",
      "ShortName": "SFX_Soldier_Attack.wav",
      "CachePath": "22/{22BB2952-1B68-46FF-A284-CB003B21E7EF}.wem"
     },
     {
      "Id": "341717970",
      "Language": "SFX",
      "Streaming": "false",
      "Location": "Memory",
      "ShortName": "SFX_Steps_Wood_03.wav",
      "CachePath": "5D/{5D2A02E1-FC98-64DD-BD3B-4E81A7DE9836}.wem"
     },
     {
      "Id": "345818729",
      "Language": "SFX",
      "Streaming": "false",
      "Location": "Memory",
      "ShortName": "SFX_Button_01.wav",
      "CachePath": "AC/{ACAB6E74-2304-2B44-F05A-F80CBC296155}.wem"
     },
     {
      "Id": "362047369",
      "Language": "SFX",
      "Streaming": "false",
      "Location": "Memory",
      "ShortName": "SFX_Wind_01.wav",
      "CachePath": "B4/{B45F6E27-1831-5540-9F77-B4FDCDBFB31B}.wem"
     },
     {
      "Id": "383253347",
      "Language": "SFX",
      "Streaming": "false",
      "Location": "Memory",
      "ShortName": "SFX_Steps_Wood_04.wav",
      "CachePath": "B2/{B2B21907-D5F6-A8D0-FBB1-D6C09D1B6F61}.wem"
     },
     {
      "Id": "393785965",
      "Language": "SFX",
      "Streaming": "false",
      "Location": "Memory",
      "ShortName": "SFX_Fire_02.wav",
      "CachePath": "6D/{6DA497E5-23FF-169F-E426-DA0578DA618D}.wem"
     },
     {
      "Id": "400074835",
      "Language": "SFX",
      "Streaming": "false",
      "Location": "Memory",
      "ShortName": "SFX_Waterfall_01.wav",
      "CachePath": "9A/{9AD8D4CA-CF92-1DC4-2BBB-F2D57EE8AE29}.wem"
     },
     {
      "Id": "465386327",
      "Language": "SFX",
      "Streaming": "false",
      "Location": "Memory",
      "ShortName": "SFX_Steps_Rock_04.wav",
      "CachePath": "A5/{A51985D6-F733-A8FD-707F-7152A74E85E5}.wem"
     },
     {
      "Id": "503395997",
      "Language": "SFX",
      "Streaming": "false",
      "Location": "Memory",
      "ShortName": "SFX_Cave_01.wav",
      "CachePath": "14/{14071845-0F88-BDD1-119C-7548C4BCC759}.wem"
     },
     {
      "Id": "514511059",
      "Language": "SFX",
      "Streaming": "false",
      "Location": "Memory",
      "ShortName": "SFX_MC_Hurt.wav",
      "CachePath": "15/{156EB0E2-EAB6-F5AB-54A1-55C12A8A5C33}.wem"
     },
     {
      "Id": "515243021",
      "Language": "SFX",
      "Streaming": "false",
      "Location": "Memory",
      "ShortName": "SFX_Pooka_Dash.wav",
      "CachePath": "B0/{B0A85975-8144-F2A3-F033-2D0F739A57A0}.wem"
     },
     {
      "Id": "555646681",
      "Language": "SFX",
      "Streaming": "false",
      "Location": "Memory",
      "ShortName": "SFX_Steps_Rock_02.wav",
      "CachePath": "57/{57CA0BF4-13BF-B1FE-FF93-720AF9552BED}.wem"
     },
     {
      "Id": "584858119",
      "Language": "SFX",
      "Streaming": "false",
      "Location": "Memory",
      "ShortName": "SFX_MC_Hit.wav",
      "CachePath": "D3/{D3F1A87A-7551-2919-2C08-8363680E230F}.wem"
     },
     {
      "Id": "620722210",
      "Language": "SFX",
      "Streaming": "false",
      "Location": "Memory",
      "ShortName": "SFX_Water_01.wav",
      "CachePath": "29/{29982D31-8E57-6F8E-9A64-947415CD530B}.wem"
     },
     {
      "Id": "679678181",
      "Language": "SFX",
      "Streaming": "false",
      "Location": "Memory",
      "ShortName": "SFX_Steps_Wood_02.wav",
      "CachePath": "5B/{5B9A55AF-7E86-7CF0-C94C-F3F2C2EB3B88}.wem"
     },
     {
      "Id": "699142529",
      "Language": "SFX",
      "Streaming": "false",
      "Location": "Memory",
      "ShortName": "SFX_MC_UltimateAttack.wav",
      "CachePath": "B8/{B856FD46-8CD4-AD27-395B-6137D1E865AA}.wem"
     },
     {
      "Id": "747169337",
      "Language": "SFX",
      "Streaming": "false",
      "Location": "Memory",
      "ShortName": "SFX_Button_03.wav",
      "CachePath": "9B/{9BE7F2E2-29BC-04BB-3F86-07679809AB0B}.wem"
     },
     {
      "Id": "773532529",
      "Language": "SFX",
      "Streaming": "false",
      "Location": "Memory",
      "ShortName": "SFX_Steps_Grass_02.wav",
      "CachePath": "5B/{5B2DFF11-E55B-38CE-B0F5-44D600FD2FD7}.wem"
     },
     {
      "Id": "779713520",
      "Language": "SFX",
      "Streaming": "false",
      "Location": "Memory",
      "ShortName": "SFX_Torch.wav",
      "CachePath": "57/{574327E7-A501-7AD5-0651-6ADD8BACD56E}.wem"
     },
     {
      "Id": "789309608",
      "Language": "SFX",
      "Streaming": "false",
      "Location": "Memory",
      "ShortName": "waterSpoutV4.wav",
      "CachePath": "DA/{DA3860BE-A495-FF55-01B9-C91093B11B27}.wem"
     },
     {
      "Id": "795005591",
      "Language": "SFX",
      "Streaming": "false",
      "Location": "Memory",
      "ShortName": "SFX_Fire_01.wav",
      "CachePath": "2C/{2CEE11AB-CCE6-28B1-ACFC-C774DD511A2E}.wem"
     },
     {
      "Id": "796020091",
      "Language": "SFX",
      "Streaming": "false",
      "Location": "Memory",
      "ShortName": "SFX_Wind_02.wav",
      "CachePath": "1F/{1F578F6E-0505-5318-6627-498F37A3CA7A}.wem"
     },
     {
      "Id": "808272714",
      "Language": "SFX",
      "Streaming": "false",
      "Location": "Memory",
      "ShortName": "SFX_Steps_Grass_03.wav",
      "CachePath": "FF/{FF9D76D5-3439-BAFC-35FD-12C0570A0AC7}.wem"
     },
     {
      "Id": "808606025",
      "Language": "SFX",
      "Streaming": "false",
      "Location": "Memory",
      "ShortName": "SFX_Pooka_Hurt.wav",
      "CachePath": "E5/{E5A76846-1CBB-B88E-9667-BECC779A0160}.wem"
     },
     {
      "Id": "827111444",
      "Language": "SFX",
      "Streaming": "false",
      "Location": "Memory",
      "ShortName": "SFX_Cave_04.wav",
      "CachePath": "59/{59959651-54B9-403D-7F6C-288FF256DBF8}.wem"
     },
     {
      "Id": "883219392",
      "Language": "SFX",
      "Streaming": "false",
      "Location": "Memory",
      "ShortName": "First_Theme.wav",
      "CachePath": "0D/{0DCBE869-C51C-382C-76D6-E81F2A0CFE34}.wem"
     },
     {
      "Id": "893119992",
      "Language": "SFX",
      "Streaming": "false",
      "Location": "Memory",
      "ShortName": "SFX_Archer_Attack_01.wav",
      "CachePath": "D1/{D17C74A8-ADEC-9112-4E6E-DD815BA64D6B}.wem"
     },
     {
      "Id": "896702479",
      "Language": "SFX",
      "Streaming": "false",
      "Location": "Memory",
      "ShortName": "SFX_Pooka_Attack.wav",
      "CachePath": "3B/{3B482F08-C87C-57C7-6A40-9C2D63DBAF80}.wem"
     },
     {
      "Id": "904930164",
      "Language": "SFX",
      "Streaming": "false",
      "Location": "Memory",
      "ShortName": "SFX_Waterfall_02.wav",
      "CachePath": "4A/{4A1AD9CE-8B23-B955-E1E0-D5A8568EB931}.wem"
     },
     {
      "Id": "954128863",
      "Language": "SFX",
      "Streaming": "false",
      "Location": "Memory",
      "ShortName": "SFX_Pooka_Death.wav",
      "CachePath": "67/{67CF7CC1-2E5C-33D3-5D3D-4C1C53208419}.wem"
     },
     {
      "Id": "979356309",
      "Language": "SFX",
      "Streaming": "false",
      "Location": "Memory",
      "ShortName": "SFX_Steps_Rock_03.wav",
      "CachePath": "14/{14385DF4-E4BC-A4F3-9A1F-145BA76C6F69}.wem"
     },
     {
      "Id": "1031840941",
      "Language": "SFX",
      "Streaming": "false",
      "Location": "Memory",
      "ShortName": "SFX_Archer_Attack_03.wav",
      "CachePath": "E1/{E18CC552-3A9A-BD01-5110-76291F0E744A}.wem"
     }
    ],
    "Events": [
     {
      "Id": "1086074370",
      "Name": "Play_First_Theme",
      "ObjectPath": "\\Events\\Default Work Unit\\Music\\Play_First_Theme",
      "GUID": "{2ABEE26A-A339-497C-A192-98ADF7BDDD2E}",
      "DurationType": "OneShot",
      "DurationMin": "100.75",
      "DurationMax": "100.75",
      "MediaRefs": [
       {
        "Id": "883219392"
       }
      ]
     },
     {
      "Id": "207755397",
      "Name": "Play_Forest",
      "ObjectPath": "\\Events\\Default Work Unit\\Music\\Play_Forest",
      "GUID": "{D9075865-6940-4B90-93EC-7CF39C73CF94}",
      "DurationType": "Infinite",
      "MediaRefs": [
       {
        "Id": "21657060"
       }
      ]
     },
     {
      "Id": "1559026790",
      "Name": "Play_SFX_Archer_Attack",
      "ObjectPath": "\\Events\\Default Work Unit\\Archer\\Play_SFX_Archer_Attack",
      "GUID": "{336BE062-556A-470A-8844-584CFE5C3926}",
      "DurationType": "OneShot",
      "DurationMin": "1.070677",
      "DurationMax": "1.070677",
      "MediaRefs": [
       {
        "Id": "893119992"
       }
      ]
     },
     {
      "Id": "2850888511",
      "Name": "Play_SFX_Archer_Overshooting",
      "ObjectPath": "\\Events\\Default Work Unit\\Archer\\Play_SFX_Archer_Overshooting",
      "GUID": "{675640FB-0ED1-4DE9-850F-B3F843B9847D}",
      "DurationType": "OneShot",
      "DurationMin": "1.3210208",
      "DurationMax": "1.3210208",
      "MediaRefs": [
       {
        "Id": "1031840941"
       }
      ]
     },
     {
      "Id": "2747797885",
      "Name": "Play_SFX_Banshee_Attack",
      "ObjectPath": "\\Events\\Default Work Unit\\Play_SFX_Banshee_Attack",
      "GUID": "{8DCB09FD-FA98-4141-A683-C798DBD02C5B}",
      "DurationType": "OneShot",
      "DurationMin": "3.4104426",
      "DurationMax": "3.4104426",
      "MediaRefs": [
       {
        "Id": "79160856"
       }
      ]
     },
     {
      "Id": "920741356",
      "Name": "Play_SFX_Button_01",
      "ObjectPath": "\\Events\\Default Work Unit\\UI\\Play_SFX_Button_01",
      "GUID": "{9D94CB30-E5C6-4289-8B93-6F9E110CFB50}",
      "DurationType": "OneShot",
      "DurationMin": "1.7555208",
      "DurationMax": "1.7555208",
      "MediaRefs": [
       {
        "Id": "345818729"
       }
      ]
     },
     {
      "Id": "920741359",
      "Name": "Play_SFX_Button_02",
      "ObjectPath": "\\Events\\Default Work Unit\\UI\\Play_SFX_Button_02",
      "GUID": "{62DDF8B0-A4BA-4ACC-8DA9-844AC5154F20}",
      "DurationType": "OneShot",
      "DurationMin": "0.74931973",
      "DurationMax": "0.74931973",
      "MediaRefs": [
       {
        "Id": "111375023"
       }
      ]
     },
     {
      "Id": "920741358",
      "Name": "Play_SFX_Button_03",
      "ObjectPath": "\\Events\\Default Work Unit\\UI\\Play_SFX_Button_03",
      "GUID": "{F7CACBC9-97CA-4359-9ECC-23516D0598E5}",
      "DurationType": "OneShot",
      "DurationMin": "0.74931973",
      "DurationMax": "0.74931973",
      "MediaRefs": [
       {
        "Id": "747169337"
       }
      ]
     },
     {
      "Id": "3434634929",
      "Name": "Play_SFX_Cave_01",
      "ObjectPath": "\\Events\\Default Work Unit\\Ambient\\Play_SFX_Cave_01",
      "GUID": "{F8F35A90-F7D5-4E9B-8C8F-90F005855173}",
      "MaxAttenuation": "30",
      "DurationType": "Infinite",
      "MediaRefs": [
       {
        "Id": "503395997"
       }
      ]
     },
     {
      "Id": "3434634930",
      "Name": "Play_SFX_Cave_02",
      "ObjectPath": "\\Events\\Default Work Unit\\Ambient\\Play_SFX_Cave_02",
      "GUID": "{EE031B47-A5B8-4400-9931-3956FB76927F}",
      "MaxAttenuation": "30",
      "DurationType": "Infinite",
      "MediaRefs": [
       {
        "Id": "303434784"
       }
      ]
     },
     {
      "Id": "3434634931",
      "Name": "Play_SFX_Cave_03",
      "ObjectPath": "\\Events\\Default Work Unit\\Ambient\\Play_SFX_Cave_03",
      "GUID": "{D44C70E5-5646-4C18-9A9D-4B7C69FA7CF1}",
      "MaxAttenuation": "30",
      "DurationType": "Infinite",
      "MediaRefs": [
       {
        "Id": "226908720"
       }
      ]
     },
     {
      "Id": "3434634932",
      "Name": "Play_SFX_Cave_04",
      "ObjectPath": "\\Events\\Default Work Unit\\Ambient\\Play_SFX_Cave_04",
      "GUID": "{F0E73809-E57C-41FD-98DA-914329093326}",
      "MaxAttenuation": "30",
      "DurationType": "Infinite",
      "MediaRefs": [
       {
        "Id": "827111444"
       }
      ]
     },
     {
      "Id": "3889642976",
      "Name": "Play_SFX_Fire_01",
      "ObjectPath": "\\Events\\Default Work Unit\\Ambient\\Play_SFX_Fire_01",
      "GUID": "{885DC419-B2DA-457F-8AB2-73EE73FAE23B}",
      "DurationType": "Infinite",
      "MediaRefs": [
       {
        "Id": "795005591"
       }
      ]
     },
     {
      "Id": "3889642979",
      "Name": "Play_SFX_Fire_02",
      "ObjectPath": "\\Events\\Default Work Unit\\Ambient\\Play_SFX_Fire_02",
      "GUID": "{E72CE92C-A7AD-450A-A57D-3CB1B60F9116}",
      "MaxAttenuation": "30",
      "DurationType": "Infinite",
      "MediaRefs": [
       {
        "Id": "393785965"
       }
      ]
     },
     {
      "Id": "917195537",
      "Name": "Play_SFX_MC_Dash",
      "ObjectPath": "\\Events\\Default Work Unit\\Player\\Play_SFX_MC_Dash",
      "GUID": "{F4A318E7-7F38-4E4D-ADAA-444E0FA8F4E9}",
      "DurationType": "OneShot",
      "DurationMin": "0.4953229",
      "DurationMax": "0.4953229",
      "MediaRefs": [
       {
        "Id": "121922950"
       }
      ]
     },
     {
      "Id": "2490745552",
      "Name": "Play_SFX_MC_Hit",
      "ObjectPath": "\\Events\\Default Work Unit\\Player\\Play_SFX_MC_Hit",
      "GUID": "{B41D8D07-91B3-4A7E-B6C9-BF8AE58BB944}",
      "DurationType": "OneShot",
      "DurationMin": "0.40754166",
      "DurationMax": "0.40754166",
      "MediaRefs": [
       {
        "Id": "584858119"
       }
      ]
     },
     {
      "Id": "2204804306",
      "Name": "Play_SFX_MC_Hurt",
      "ObjectPath": "\\Events\\Default Work Unit\\Player\\Play_SFX_MC_Hurt",
      "GUID": "{C782CB6D-A703-4F52-B3A3-945AEF8E9D3C}",
      "DurationType": "OneShot",
      "DurationMin": "0.52405894",
      "DurationMax": "0.52405894",
      "MediaRefs": [
       {
        "Id": "514511059"
       }
      ]
     },
     {
      "Id": "2177541458",
      "Name": "Play_SFX_MC_NormalAttack_01",
      "ObjectPath": "\\Events\\Default Work Unit\\Player\\Play_SFX_MC_NormalAttack_01",
      "GUID": "{F4D2EE4F-9BAD-48A2-99F0-C8D3218954AF}",
      "DurationType": "OneShot",
      "DurationMin": "1.0953177",
      "DurationMax": "1.0953177",
      "MediaRefs": [
       {
        "Id": "275805708"
       }
      ]
     },
     {
      "Id": "1030865972",
      "Name": "Play_SFX_MC_UltimateAttack",
      "ObjectPath": "\\Events\\Default Work Unit\\Player\\Play_SFX_MC_UltimateAttack",
      "GUID": "{F63F26EC-FA88-454E-9485-2CEF3D1CA545}",
      "DurationType": "OneShot",
      "DurationMin": "3.5958333",
      "DurationMax": "3.5958333",
      "MediaRefs": [
       {
        "Id": "699142529"
       }
      ]
     },
     {
      "Id": "2845739403",
      "Name": "Play_SFX_Pooka_Attack",
      "ObjectPath": "\\Events\\Default Work Unit\\Pooka\\Play_SFX_Pooka_Attack",
      "GUID": "{CCC7245C-724F-48D0-B839-B9C9557498FA}",
      "DurationType": "OneShot",
      "DurationMin": "0.24922903",
      "DurationMax": "0.24922903",
      "MediaRefs": [
       {
        "Id": "896702479"
       }
      ]
     },
     {
      "Id": "3129736499",
      "Name": "Play_SFX_Pooka_BuryDown",
      "ObjectPath": "\\Events\\Default Work Unit\\Pooka\\Play_SFX_Pooka_BuryDown",
      "GUID": "{B90088D0-50C3-45A2-B5F7-CF765AD34450}",
      "DurationType": "OneShot",
      "DurationMin": "1.4868646",
      "DurationMax": "1.4868646",
      "MediaRefs": [
       {
        "Id": "102221775"
       }
      ]
     },
     {
      "Id": "3198435252",
      "Name": "Play_SFX_Pooka_BuryUp",
      "ObjectPath": "\\Events\\Default Work Unit\\Pooka\\Play_SFX_Pooka_BuryUp",
      "GUID": "{910AF09D-3081-449F-8755-51D461BDA6C5}",
      "DurationType": "OneShot",
      "DurationMin": "1.8985034",
      "DurationMax": "1.8985034",
      "MediaRefs": [
       {
        "Id": "285188273"
       }
      ]
     },
     {
      "Id": "2385944011",
      "Name": "Play_SFX_Pooka_Dash",
      "ObjectPath": "\\Events\\Default Work Unit\\Pooka\\Play_SFX_Pooka_Dash",
      "GUID": "{A60F8E37-2D30-4A32-B425-AF5168074FE1}",
      "DurationType": "OneShot",
      "DurationMin": "1.8513379",
      "DurationMax": "1.8513379",
      "MediaRefs": [
       {
        "Id": "515243021"
       }
      ]
     },
     {
      "Id": "4271776059",
      "Name": "Play_SFX_Pooka_Death",
      "ObjectPath": "\\Events\\Default Work Unit\\Pooka\\Play_SFX_Pooka_Death",
      "GUID": "{66A5FD07-A018-4D1A-A4AF-0CB759D4D05D}",
      "DurationType": "OneShot",
      "DurationMin": "2.744",
      "DurationMax": "2.744",
      "MediaRefs": [
       {
        "Id": "954128863"
       }
      ]
     },
     {
      "Id": "1906970548",
      "Name": "Play_SFX_Pooka_Hurt",
      "ObjectPath": "\\Events\\Default Work Unit\\Pooka\\Play_SFX_Pooka_Hurt",
      "GUID": "{0973842B-0844-49DB-A436-58189E328437}",
      "DurationType": "OneShot",
      "DurationMin": "0.3383125",
      "DurationMax": "0.3383125",
      "MediaRefs": [
       {
        "Id": "808606025"
       }
      ]
     },
     {
      "Id": "3285336459",
      "Name": "Play_SFX_Soldier_Attack",
      "ObjectPath": "\\Events\\Default Work Unit\\Soldier\\Play_SFX_Soldier_Attack",
      "GUID": "{A0D2FE1A-940A-45E1-AB55-9C66370C27FA}",
      "DurationType": "OneShot",
      "DurationMin": "0.71183336",
      "DurationMax": "0.71183336",
      "MediaRefs": [
       {
        "Id": "327978205"
       }
      ]
     },
     {
      "Id": "879946080",
      "Name": "Play_SFX_Steps_Grass",
      "ObjectPath": "\\Events\\Default Work Unit\\Play_SFX_Steps_Grass",
      "GUID": "{812EBAFA-F6A3-4326-AF09-2E01CD2B152F}",
      "DurationType": "OneShot",
      "DurationMin": "0.34133786",
      "DurationMax": "0.7991383",
      "MediaRefs": [
       {
        "Id": "93382910"
       },
       {
        "Id": "773532529"
       },
       {
        "Id": "808272714"
       }
      ]
     },
     {
      "Id": "2099665009",
      "Name": "Play_SFX_Steps_Rock",
      "ObjectPath": "\\Events\\Default Work Unit\\Play_SFX_Steps_Rock",
      "GUID": "{8E14E641-E8B3-49B8-A15F-D65947122141}",
      "DurationType": "OneShot",
      "DurationMin": "0.175375",
      "DurationMax": "0.4774375",
      "MediaRefs": [
       {
        "Id": "153266711"
       },
       {
        "Id": "465386327"
       },
       {
        "Id": "555646681"
       },
       {
        "Id": "979356309"
       }
      ]
     },
     {
      "Id": "2418067177",
      "Name": "Play_SFX_Steps_Wood",
      "ObjectPath": "\\Events\\Default Work Unit\\Play_SFX_Steps_Wood",
      "GUID": "{D5FD5DCA-9B41-431B-A0C8-963E77264615}",
      "DurationType": "OneShot",
      "DurationMin": "0.29966667",
      "DurationMax": "0.50673956",
      "MediaRefs": [
       {
        "Id": "113287012"
       },
       {
        "Id": "341717970"
       },
       {
        "Id": "383253347"
       },
       {
        "Id": "679678181"
       }
      ]
     },
     {
      "Id": "3055317224",
      "Name": "Play_SFX_TreeOfLife_02",
      "ObjectPath": "\\Events\\Default Work Unit\\Ambient\\Play_SFX_TreeOfLife_02",
      "GUID": "{08C4734D-83DF-4984-A7BA-A5720FB4D881}",
      "DurationType": "OneShot",
      "DurationMin": "5.7251773",
      "DurationMax": "5.7251773",
      "MediaRefs": [
       {
        "Id": "5830356"
       }
      ]
     },
     {
      "Id": "3055317225",
      "Name": "Play_SFX_TreeOfLife_03",
      "ObjectPath": "\\Events\\Default Work Unit\\Ambient\\Play_SFX_TreeOfLife_03",
      "GUID": "{E3F6244C-180E-4E47-8E93-5EDF3A902CAB}",
      "DurationType": "OneShot",
      "DurationMin": "3.4046147",
      "DurationMax": "3.4046147",
      "MediaRefs": [
       {
        "Id": "237654140"
       }
      ]
     },
     {
      "Id": "3212841747",
      "Name": "Play_SFX_Water_01",
      "ObjectPath": "\\Events\\Default Work Unit\\Ambient\\Play_SFX_Water_01",
      "GUID": "{EAB33356-9383-4F88-A7B3-C71A20E603B2}",
      "MaxAttenuation": "30",
      "DurationType": "Infinite",
      "MediaRefs": [
       {
        "Id": "620722210"
       }
      ]
     },
     {
      "Id": "278128852",
      "Name": "Play_SFX_Water_Spouts",
      "ObjectPath": "\\Events\\Default Work Unit\\Traps\\Play_SFX_Water_Spouts",
      "GUID": "{5F567761-65EA-4F15-AC5A-D94F8897D4A5}",
      "DurationType": "OneShot",
      "DurationMin": "3.208079",
      "DurationMax": "3.208079",
      "MediaRefs": [
       {
        "Id": "789309608"
       }
      ]
     },
     {
      "Id": "1233267134",
      "Name": "Play_SFX_Waterfall_01",
      "ObjectPath": "\\Events\\Default Work Unit\\Ambient\\Play_SFX_Waterfall_01",
      "GUID": "{1267F9A2-A83F-4038-AB35-D6FF52B3CC3F}",
      "MaxAttenuation": "30",
      "DurationType": "Infinite",
      "MediaRefs": [
       {
        "Id": "400074835"
       }
      ]
     },
     {
      "Id": "1233267133",
      "Name": "Play_SFX_Waterfall_02",
      "ObjectPath": "\\Events\\Default Work Unit\\Ambient\\Play_SFX_Waterfall_02",
      "GUID": "{F459D214-3414-43A2-997D-9A3F07436C8F}",
      "MaxAttenuation": "30",
      "DurationType": "Infinite",
      "MediaRefs": [
       {
        "Id": "904930164"
       }
      ]
     },
     {
      "Id": "4018713014",
      "Name": "Play_SFX_Wind_01",
      "ObjectPath": "\\Events\\Default Work Unit\\Ambient\\Play_SFX_Wind_01",
      "GUID": "{596D568A-4C77-45BD-AD51-436B8A895265}",
      "MaxAttenuation": "30",
      "DurationType": "Infinite",
      "MediaRefs": [
       {
        "Id": "362047369"
       }
      ]
     },
     {
      "Id": "4018713013",
      "Name": "Play_SFX_Wind_02",
      "ObjectPath": "\\Events\\Default Work Unit\\Ambient\\Play_SFX_Wind_02",
      "GUID": "{818FB92D-26E9-4B1D-9804-0C6E27469D32}",
      "MaxAttenuation": "30",
      "DurationType": "Infinite",
      "MediaRefs": [
       {
        "Id": "796020091"
       }
      ]
     },
     {
      "Id": "2025845440",
      "Name": "Play_Torch",
      "ObjectPath": "\\Events\\Default Work Unit\\Ambient\\Play_Torch",
      "GUID": "{60E7CCF7-F58F-4F24-B61A-B5039D36FAD7}",
      "MaxAttenuation": "30",
      "DurationType": "Infinite",
      "MediaRefs": [
       {
        "Id": "779713520"
       }
      ]
     }
    ],
    "GameParameters": [
     {
      "Id": "1908158473",
      "Name": "Pitch",
      "ObjectPath": "\\Game Parameters\\Default Work Unit\\Basic parameters\\Pitch",
      "GUID": "{D3F43A1C-F866-482C-A368-2D33F58CA992}"
     },
     {
      "Id": "2395249601",
      "Name": "Spatialization",
      "ObjectPath": "\\Game Parameters\\Default Work Unit\\Basic parameters\\Spatialization",
      "GUID": "{567C7AE0-F9CF-4A83-B523-D2869D369424}"
     },
     {
      "Id": "2415836739",
      "Name": "Volume",
      "ObjectPath": "\\Game Parameters\\Default Work Unit\\Basic parameters\\Volume",
      "GUID": "{30DC10CF-4BAB-456C-9C95-4F67C938F642}"
     }
    ]
   }
  ],
  "FileHash": "{FB7D4118-B0EA-E1D2-D855-B57B9B7255A5}"
 }
}